src/__init__.py
src/extract_quality_standards.py
src/fill_quality_standards.py
src/server.py
cantonbio_ra_doc_mcp-0.1.1.dist-info/METADATA
cantonbio_ra_doc_mcp-0.1.1.dist-info/WHEEL
cantonbio_ra_doc_mcp-0.1.1.dist-info/RECORD
