Metadata-Version: 2.4
Name: cantonbio-ra-doc-mcp
Version: 0.1.1
Summary: RA注册文档助手，协助处理注册文档的编写和校验工作
Requires-Python: >=3.11
Requires-Dist: mcp[cli]>=1.15.0
Requires-Dist: python-docx>=1.1.0
Provides-Extra: dev
Requires-Dist: pytest-cov>=4.1.0; extra == 'dev'
Requires-Dist: pytest>=8.0.0; extra == 'dev'
